<?xml version="1.0" encoding="utf-8" standalone="yes"?>
<window>
<id>49852</id>
<defaultcontrol>11</defaultcontrol>
<allowoverlay>yes</allowoverlay>
<controls>

	<import>common.window.4tr_recordings.xml</import>
	<import>common.time.xml</import>
	
	<control>
		<animation effect="fade" time="250">WindowOpen</animation>
		<animation effect="fade" time="250">WindowClose</animation>
		<type>label</type>
		<id>1</id>
		<posX>185</posX>
		<posY>38</posY>
		<width>800</width>
		<label>604</label>
		<textcolor>6aa5cb</textcolor>
		<font>font22</font>
		<visible>facadeview.list</visible>
	</control>

	
	<control>
		<type>actiongroup</type>
		<description>action menu</description>
		<defaultcontrol>2</defaultcontrol>
		<onexit>50</onexit>
		<dimColor>00ffffff</dimColor>
		<buttonX>0</buttonX>
		<buttonY>0</buttonY>
		<buttonwidth>521</buttonwidth>
		<buttonheight>1080</buttonheight>
		
		<control>
			<type>image</type>
			<id>0</id>
			<width>1920</width>
			<height>1080</height>
			<texture>semi_trans_back_hidden_menu.png</texture>
			<visible>!Control.HasFocus(50)</visible>
			<animation effect="fade" time="450">visible</animation>
			<animation effect="fade" time="400">hidden</animation>
		</control>
		
	<control>
		<type>group</type>
		<animation effect="fade" time="250">WindowOpen</animation>
		<animation effect="fade" time="0">WindowClose</animation>
		<animation effect="slide" start="-150,0" end="0,0" tween="quadratic" easing="in" time="200" delay="0">visible</animation>
		<animation effect="fade" time="250">visible</animation>
		<animation effect="fade" time="0">hidden</animation>
		<control>
			<type>image</type>
			<id>0</id>
			<posY>15</posY>
			<posX>0</posX>
			<width>631</width>
			<height>1044</height>
			<texture>menu_bg.png</texture>
			<visible>!Control.HasFocus(50)</visible>
		</control>
	
		<control>
			<description>Heading text label</description>
			<type>label</type>
			<id>1</id>
			<posX>136</posX>
			<posY>128</posY>
			<label>924</label>
			<font>font22</font>
			<textcolor>ffffff</textcolor>
		</control>	
				
			<control>
				<type>button</type>
				<description>View-As button</description>
				<id>2</id>
				<onleft>50</onleft>
				<onright>50</onright>
				<onup>5</onup>
				<ondown>3</ondown>
				<label>100</label>
				<textureFocus>hiddenmenu_item_selected.png</textureFocus>
				<textureNoFocus>-</textureNoFocus>
				<posX>69</posX>
				<posY>215</posY>
				<width>459</width>
				<height>70</height>
				<textXOff>66</textXOff>
				<textYOff>17</textYOff>
			</control>

			<control>
				<type>button</type>
				<description>All,Genre,Channel button</description>
				<id>3</id>
				<onleft>50</onleft>
				<onright>50</onright>
				<onup>2</onup>
				<ondown>4</ondown>
				<label>457</label>
				<textureFocus>hiddenmenu_item_selected.png</textureFocus>
				<textureNoFocus>-</textureNoFocus>
				<posX>69</posX>
				<posY>285</posY>
				<width>459</width>
				<height>70</height>
				<textXOff>66</textXOff>
				<textYOff>17</textYOff>
			</control>
			
			<control>
				<type>sortbutton</type>
				<id>4</id>
				<onleft>50</onleft>
				<onright>50</onright>
				<onup>3</onup>
				<ondown>5</ondown>
				<label>620</label>
				<textureFocus>hiddenmenu_item_selected.png</textureFocus>
				<textureNoFocus>-</textureNoFocus>
				<posX>69</posX>
				<posY>355</posY>
				<width>459</width>
				<height>70</height>
				<textXOff>66</textXOff>
				<textYOff>17</textYOff>
				<offsetSortButtonX>260</offsetSortButtonX>
				<offsetSortButtonY>27</offsetSortButtonY>
			</control>

			<control>
				<type>button</type>
				<description>radioguide button</description>
				<id>5</id>
				<onleft>50</onleft>
				<onright>50</onright>
				<onup>4</onup>
				<ondown>2</ondown>
				<hyperlink>762</hyperlink>
				<label>533</label>
				<textureFocus>hiddenmenu_item_selected.png</textureFocus>
				<textureNoFocus>-</textureNoFocus>
				<posX>69</posX>
				<posY>425</posY>
				<width>459</width>
				<height>70</height>
				<textXOff>66</textXOff>
				<textYOff>17</textYOff>			
			</control>
		
		</control>
	</control>
	
	<control>
		<type>group</type>
		<description>group element</description>
		<id>0</id>
		<posX>455</posX>
		<posY>116</posY>
		<width>778</width>
		<dimColor>ffffffff</dimColor>
		<height>583</height>
		<animation effect="fade" start="0" end="100" time="300" delay="350">WindowOpen</animation>
		<animation effect="fade" start="100" end="0" time="0" delay="0">WindowClose</animation>

		<!-- List -->
		
		<control>
			<id>0</id>
			<type>image</type>
			<posX>74</posX>
			<posY>245</posY>
			<width>421</width>
			<height>238</height>
			<texture flipY="true" diffuse="Thumb_Mask.png" mask="recordings_thumb_mask.png">defaultTVBig.png</texture>
			<visible>facadeview.list+[!control.hasthumb(500)|string.equals(#selectedthumb,defaultFolderBig.png)]+!string.equals(#selecteditem,..)</visible>
			<animation effect="fade" start="0" end="100" time="300" delay="350">WindowOpen</animation>
			<animation effect="fade" start="100" end="0" time="0" delay="0">WindowClose</animation>
		</control>
		
		<control>
			<id>500</id>
			<type>image</type>
			<posX>74</posX>
			<posY>245</posY>
			<width>421</width>
			<height>238</height>
			<texture flipY="true" diffuse="Thumb_Mask.png" mask="recordings_thumb_mask.png">#selectedthumb</texture>
			<visible>facadeview.list+!string.equals(#selectedthumb,defaultFolderBig.png)+!string.equals(#selecteditem,..)</visible>
			<animation effect="fade" start="0" end="100" time="300" delay="350">WindowOpen</animation>
			<animation effect="fade" start="100" end="0" time="0" delay="0">WindowClose</animation>
		</control>
		
		<control>
			<id>0</id>
			<type>image</type>
			<posX>7</posX>
			<posY>177</posY>
			<width>556</width>
			<height>373</height>
			<texture>recordings_thumb_shadow.png</texture>
			<visible>facadeview.list</visible>
			<animation effect="fade" start="0" end="100" time="300" delay="350">WindowOpen</animation>
			<animation effect="fade" start="100" end="0" time="0" delay="0">WindowClose</animation>
		</control>
		
		<control>
			<id>0</id>
			<type>image</type>
			<posX>536</posX>
			<posY>364</posY>
			<width>187</width>
			<height>119</height>
			<texture>tv_logo_bg.png</texture>
			<visible>facadeview.list+!string.equals(#selecteditem,..)</visible>
			<animation effect="fade" start="0" end="100" time="300" delay="350">WindowOpen</animation>
			<animation effect="fade" start="100" end="0" time="0" delay="0">WindowClose</animation>
		</control>
		
		<control>
			<id>0</id>
			<type>image</type>
			<posX>585</posX>
			<posY>378</posY>
			<width>90</width>
			<height>90</height>
			<texture>#Radio.RecordedTV.thumb</texture>
			<visible>facadeview.list</visible>
			<animation effect="fade" start="0" end="100" time="300" delay="350">WindowOpen</animation>
			<animation effect="fade" start="100" end="0" time="0" delay="0">WindowClose</animation>
		</control>
		
<!-- 		<control>
			<description>Current program channel</description>
			<type>label</type>
			<id>0</id>
			<posX>555</posX>
			<posY>180</posY>
			<label>#Radio.RecordedTV.Channel</label>
			<font>AvalonLight18</font>
			<textcolor>6aa5cb</textcolor>
			<visible>facadeview.list</visible>
		</control> -->
		
		<control>
			<type>label</type>
			<description>Current program time</description>
			<id>0</id>
			<posX>74</posX>
			<posY>578</posY>
			<textcolor>6aa5cb</textcolor>
			<font>AvalonLight14</font>
			<animation effect="fade" start="0" end="100" time="300" delay="350">WindowOpen</animation>
			<animation effect="fade" start="100" end="0" time="0" delay="0">WindowClose</animation>
			<label>#Radio.RecordedTV.Time #Radio.RecordedTV.Genre</label>
			<visible>facadeview.list</visible>
		</control>
		
		<control>
			<type>textboxscrollup</type>
			<description>Description1</description>
			<id>0</id>
			<posX>74</posX>
			<posY>630</posY>
			<width>780</width>
			<height>230</height>
			<label>#Radio.RecordedTV.Description</label>
			<visible>facadeview.list</visible>
		</control>
		
		<!-- Thumb -->
		
		<control>
			<description>Current program channel</description>
			<type>label</type>
			<id>0</id>
			<posX>515</posX>
			<posY>610</posY>
			<label>#Radio.RecordedTV.Channel</label>
			<font>Segoe Light18</font>
			<textcolor>6aa5cb</textcolor>
			<align>right</align>
			<visible>facadeview.smallicons|facadeview.largeicons</visible>
		</control>
		
		<control>
			<type>label</type>
			<description>Current program genre</description>
			<id>0</id>
			<posX>515</posX>
			<posY>643</posY>
			<textcolor>6aa5cb</textcolor>
			<font>Segoe Light18</font>
			<label>#Radio.RecordedTV.Genre</label>
			<align>right</align>
			<visible>facadeview.smallicons|facadeview.largeicons</visible>
		</control>
			
		<control>
			<type>label</type>
			<description>Current program time</description>
			<id>0</id>
			<posX>515</posX>
			<posY>682</posY>
			<textcolor>6aa5cb</textcolor>
			<font>Segoe Light18</font>
			<label>#Radio.RecordedTV.Time</label>
			<align>right</align>
			<visible>facadeview.smallicons|facadeview.largeicons</visible>
		</control>
		
		<control>
			<type>textboxscrollup</type>
			<description>Description1</description>
			<id>0</id>
			<posX>555</posX>
			<posY>614</posY>
			<width>741</width>
			<height>134</height>
			<label>#Radio.RecordedTV.Description</label>
			<visible>facadeview.smallicons|facadeview.largeicons</visible>
		</control>
		
			<!-- Filmstrip -->
			
		<control>
			<type>label</type>
			<description>Current program time</description>
			<id>0</id>
			<posX>515</posX>
			<posY>682</posY>
			<textcolor>6aa5cb</textcolor>
			<font>Segoe Light18</font>
			<label>#selecteditem2</label>
			<visible>facadeview.filmstrip</visible>
		</control>
	</control>	
	
	<control>
		<animation effect="slide" start="-60,0" end="0,0" tween="quadratic" easing="in" time="400" delay="600">WindowOpen</animation>
		<animation effect="slide" start="0,0" end="-60,0" tween="quadratic" easing="in" time="400" delay="100">WindowClose</animation>
		<id>1</id>
		<type>image</type>
		<posY>440</posY>
		<width>64</width>
		<height>199</height>
		<texture>hiddenmenu_tab.png</texture>
		<visible>[facadeview.list|facadeview.smallicons|facadeview.largeicons]+Control.HasFocus(50)</visible>
	</control>

	<control>
		<animation effect="slide" start="0,-60" end="0,0" tween="quadratic" easing="in" time="400" delay="600">WindowOpen</animation>
		<animation effect="slide" start="0,0" end="0,-60" tween="quadratic" easing="in" time="400" delay="100">WindowClose</animation>
		<id>1</id>
		<type>image</type>
		<posX>858</posX>
		<posY>0</posY>
		<texture>hiddenmenu_tab_up.png</texture>
		<visible>facadeview.filmstrip+Control.HasFocus(50)</visible>
	</control>
	
	<import>common.facade.recordings.xml</import>
</controls>
</window>