<?xml version="1.0" encoding="utf-8" standalone="yes"?>
<window>
<controls>

	<control>
		<description>BG</description>
		<type>image</type>
		<id>1</id>
		<width>1920</width>
		<height>1080</height>
	</control>

	<control>
		<animation effect="fade" time="100">WindowOpen</animation>
		<animation effect="fade" time="100">WindowClose</animation>
		<type>label</type>
		<id>1</id>
		<posX>552</posX>
		<posY>30</posY>
		<width>500</width>
		<height>100</height>
		<label>#header.label</label>
		<textcolor>6aa5cb</textcolor>
		<font>Segoe Light40</font>
	</control>
	
	<control>
		<animation effect="fade" time="100">WindowOpen</animation>
		<animation effect="fade" time="100">WindowClose</animation>
		<type>label</type>
		<id>1</id>
		<posX>552</posX>
		<posY>120</posY>
		<width>500</width>
		<height>100</height>
		<label>5</label>
		<font>Segoe Light22</font>
	</control>

	<control>
		<description>Hover image</description>
		<type>image</type>
		<id>1</id>
		<posX>136</posX>
		<posY>500</posY>
		<width>286</width>
		<height>197</height>
		<texture>#header.hover</texture>
		<visible>!videoplayer.usingoverlays</visible>
		<animation effect="fade" time="250">WindowOpen</animation>
		<animation effect="fade" time="250">WindowClose</animation>
	</control>

</controls>
</window>
